qiniu_sdk_alpha-0.0.2.dist-info/METADATA
qiniu_sdk_alpha-0.0.2.dist-info/WHEEL
qiniu_sdk_alpha-0.0.2.dist-info/license_files/LICENSE
qiniu_sdk_alpha.libs/libssl-e86845de.so.1.1
qiniu_sdk_alpha.libs/libcrypto-da090ac7.so.1.1
qiniu_sdk_alpha/__init__.py
qiniu_sdk_alpha/qiniu_sdk_alpha.abi3.so
qiniu_sdk_alpha-0.0.2.dist-info/RECORD
