Metadata-Version: 2.1
Name: qiniu-sdk-alpha
Version: 0.0.2
Classifier: Programming Language :: Rust
Classifier: Programming Language :: Python :: Implementation :: CPython
Classifier: Programming Language :: Python :: Implementation :: PyPy
Classifier: Development Status :: 5 - Production/Stable
Classifier: Intended Audience :: Developers
Classifier: Operating System :: OS Independent
Classifier: Programming Language :: Python :: 3.8
Classifier: Programming Language :: Python :: 3.9
Classifier: Programming Language :: Python :: 3.10
Classifier: License :: OSI Approved :: MIT License
Requires-Dist: maturin>=0.13,<0.14
Requires-Dist: Sphinx>=4.0.0,<5.0.0; extra == 'tests'
Requires-Dist: aiofiles>=0.8.0,<0.9.0; extra == 'tests'
Requires-Dist: aiohttp>=3.0.0,<4.0.0; extra == 'tests'
Provides-Extra: tests
License-File: LICENSE
Summary: Qiniu Rust SDK Bindings to Python
Keywords: qiniu,storage,python
Home-Page: https://www.qiniu.com
Author: Rong Zhou <zhourong@qiniu.com>, Shanghai Qiniu Information Technologies Co., Ltd.
Author-email: Rong Zhou <zhourong@qiniu.com>
License: MIT
Requires-Python: >=3.8
Project-URL: Source Code, https://github.com/bachue/rust-sdk-python-bindings.git
